pydirl/__init__.py
pydirl/app.py
pydirl/cli.py
pydirl/files_utils.py
pydirl/tools.py
pydirl/static/dirl.js
pydirl/static/style.css
pydirl/templates/error.html
pydirl/templates/template.html
pydirl-0.3.2.dist-info/DESCRIPTION.rst
pydirl-0.3.2.dist-info/METADATA
pydirl-0.3.2.dist-info/RECORD
pydirl-0.3.2.dist-info/WHEEL
pydirl-0.3.2.dist-info/entry_points.txt
pydirl-0.3.2.dist-info/metadata.json
pydirl-0.3.2.dist-info/top_level.txt
src/__init__.py
src/app.py
src/cli.py
src/files_utils.py
src/tools.py
src/static/dirl.js
src/templates/error.html
src/templates/template.html
test/__init__.py
test/test_basic.py
test/test_exclude.py
test/test_single_file_mode.py
test/test_zipped.py
