Metadata-Version: 2.0
Name: pydirl
Version: 0.3.2
Summary: Quick file sharing solution
Home-page: https://github.com/ael-code/pydirl
Author: UNKNOWN
Author-email: UNKNOWN
License: GPLv3
Platform: UNKNOWN
Classifier: Development Status :: 4 - Beta
Classifier: Framework :: Flask
Classifier: License :: OSI Approved :: GNU Affero General Public License v3
Classifier: Operating System :: Unix
Classifier: Operating System :: Microsoft :: Windows
Classifier: Operating System :: MacOS
Classifier: Programming Language :: Python :: 2
Classifier: Programming Language :: Python :: 3
Classifier: Topic :: Communications :: File Sharing
Requires-Dist: click
Requires-Dist: flask
Requires-Dist: flask-bootstrap (<4)
Requires-Dist: gevent
Requires-Dist: zipstream
